features/__init__.py
features/main.py
finbourne_sdk_utils/__init__.py
finbourne_sdk_utils/cocoon/__init__.py
finbourne_sdk_utils/cocoon/async_tools.py
finbourne_sdk_utils/cocoon/cocoon.py
finbourne_sdk_utils/cocoon/cocoon_printer.py
finbourne_sdk_utils/cocoon/dateorcutlabel.py
finbourne_sdk_utils/cocoon/instruments.py
finbourne_sdk_utils/cocoon/properties.py
finbourne_sdk_utils/cocoon/seed_sample_data.py
finbourne_sdk_utils/cocoon/systemConfiguration.py
finbourne_sdk_utils/cocoon/transaction_type_upload.py
finbourne_sdk_utils/cocoon/utilities.py
finbourne_sdk_utils/cocoon/validator.py
finbourne_sdk_utils/cocoon/config/domain_settings.json
finbourne_sdk_utils/cocoon/config/seed_sample_data.json
finbourne_sdk_utils/extract/__init__.py
finbourne_sdk_utils/extract/group_holdings.py
finbourne_sdk_utils/iam/__init__.py
finbourne_sdk_utils/iam/roles.py
finbourne_sdk_utils/jupyter_tools/__init__.py
finbourne_sdk_utils/jupyter_tools/hide_code_button.py
finbourne_sdk_utils/jupyter_tools/stop_execution.py
finbourne_sdk_utils/logger/LusidLogger.py
finbourne_sdk_utils/logger/__init__.py
finbourne_sdk_utils/lpt/__init__.py
finbourne_sdk_utils/lpt/back_compat.py
finbourne_sdk_utils/lpt/cash_ladder.py
finbourne_sdk_utils/lpt/connect_lusid.py
finbourne_sdk_utils/lpt/connect_none.py
finbourne_sdk_utils/lpt/connect_token.py
finbourne_sdk_utils/lpt/dfq.py
finbourne_sdk_utils/lpt/either.py
finbourne_sdk_utils/lpt/get_instruments.py
finbourne_sdk_utils/lpt/lpt.py
finbourne_sdk_utils/lpt/lse.py
finbourne_sdk_utils/lpt/map_instruments.py
finbourne_sdk_utils/lpt/pager.py
finbourne_sdk_utils/lpt/record.py
finbourne_sdk_utils/lpt/refreshing_token.py
finbourne_sdk_utils/lpt/search_instruments.py
finbourne_sdk_utils/lpt/stdargs.py
finbourne_sdk_utils/lpt/txn_config.py
finbourne_sdk_utils/lpt/txn_config_yaml.py
finbourne_sdk_utils/pandas_utils/__init__.py
finbourne_sdk_utils/pandas_utils/lusid_pandas.py
finbourne_sdk_utils-0.0.33.dist-info/LICENSE
finbourne_sdk_utils-0.0.33.dist-info/METADATA
finbourne_sdk_utils-0.0.33.dist-info/WHEEL
finbourne_sdk_utils-0.0.33.dist-info/top_level.txt
finbourne_sdk_utils-0.0.33.dist-info/RECORD
